pycondusco/__init__.py
pycondusco/run_pipeline.py
pycondusco/run_pipeline_gbq.py
pycondusco/test/__init__.py
pycondusco/test/test_gbq.py
pycondusco/test/test_run_pipeline.py
pycondusco/test/test_run_pipeline_gbq.py
pycondusco-0.1.0.dist-info/LICENSE.txt
pycondusco-0.1.0.dist-info/METADATA
pycondusco-0.1.0.dist-info/WHEEL
pycondusco-0.1.0.dist-info/top_level.txt
pycondusco-0.1.0.dist-info/RECORD
