Metadata-Version: 2.1
Name: pycondusco
Version: 0.1.0
Summary: pycondusco lets you run a function iteratively, passing it the rows of a dataframe or the results of a query.
Home-page: https://github.com/ras44/pycondusco
Author: Roland Stevenson
Author-email: roland@rmg-services.com
License: UNKNOWN
Platform: UNKNOWN
Requires-Dist: google-cloud-bigquery (>=1.0.0)
